aiomysql/__init__.py
aiomysql/connection.py
aiomysql/cursors.py
aiomysql/log.py
aiomysql/pool.py
aiomysql/utils.py
aiomysql/sa/__init__.py
aiomysql/sa/connection.py
aiomysql/sa/engine.py
aiomysql/sa/exc.py
aiomysql/sa/result.py
aiomysql/sa/transaction.py
aiomysql_fork/__init__.py
aiomysql_fork/connection.py
aiomysql_fork/cursors.py
aiomysql_fork/log.py
aiomysql_fork/pool.py
aiomysql_fork/utils.py
aiomysql_fork/sa/__init__.py
aiomysql_fork/sa/connection.py
aiomysql_fork/sa/engine.py
aiomysql_fork/sa/exc.py
aiomysql_fork/sa/result.py
aiomysql_fork/sa/transaction.py
aiomysql_fork-0.0.2.dist-info/LICENSE
aiomysql_fork-0.0.2.dist-info/METADATA
aiomysql_fork-0.0.2.dist-info/WHEEL
aiomysql_fork-0.0.2.dist-info/top_level.txt
aiomysql_fork-0.0.2.dist-info/RECORD
